README.md
setup.py
ACSConv.egg-info/PKG-INFO
ACSConv.egg-info/SOURCES.txt
ACSConv.egg-info/dependency_links.txt
ACSConv.egg-info/requires.txt
ACSConv.egg-info/top_level.txt
ACSConv.egg-info/zip-safe
acsconv/__init__.py
acsconv/utils.py
acsconv/converters/__init__.py
acsconv/converters/acsconv_converter.py
acsconv/converters/base_converter.py
acsconv/converters/conv2_5d_converter.py
acsconv/converters/conv3d_converter.py
acsconv/converters/soft_acsconv_converter.py
acsconv/models/__init__.py
acsconv/models/acsunet.py
acsconv/models/convnext.py
acsconv/models/densenet.py
acsconv/models/resnet.py
acsconv/models/vgg.py
acsconv/operators/__init__.py
acsconv/operators/acsconv.py
acsconv/operators/base_acsconv.py
acsconv/operators/conv2_5d.py
acsconv/operators/functional.py
acsconv/operators/soft_acsconv.py