Metadata-Version: 2.1
Name: ACSConv
Version: 0.1.1
Summary: [IEEE JBHI] Reinventing 2D Convolutions for 3D Images
Home-page: https://github.com/M3DV/ACSConv
Author: Jiancheng Yang and Xiaoyang Huang
Author-email: jekyll4168@sjtu.edu.cn
License: Apache-2.0 License
Platform: UNKNOWN
Classifier: License :: OSI Approved :: Apache Software License
Classifier: Programming Language :: Python
Classifier: Programming Language :: Python :: 3 :: Only
Requires-Python: >=3.6.0
